optimade/__init__.py
optimade/exceptions.py
optimade/utils.py
optimade/warnings.py
optimade/adapters/__init__.py
optimade/adapters/base.py
optimade/adapters/exceptions.py
optimade/adapters/logger.py
optimade/adapters/warnings.py
optimade/adapters/references/__init__.py
optimade/adapters/references/adapter.py
optimade/adapters/structures/__init__.py
optimade/adapters/structures/adapter.py
optimade/adapters/structures/aiida.py
optimade/adapters/structures/ase.py
optimade/adapters/structures/cif.py
optimade/adapters/structures/jarvis.py
optimade/adapters/structures/proteindatabank.py
optimade/adapters/structures/pymatgen.py
optimade/adapters/structures/utils.py
optimade/client/__init__.py
optimade/client/cli.py
optimade/client/client.py
optimade/client/utils.py
optimade/filterparser/__init__.py
optimade/filterparser/lark_parser.py
optimade/filtertransformers/__init__.py
optimade/filtertransformers/base_transformer.py
optimade/filtertransformers/elasticsearch.py
optimade/filtertransformers/mongo.py
optimade/grammar/__init__.py
optimade/grammar/v1.0.0.lark
optimade/grammar/v1.0.1.lark
optimade/grammar/v1.1.0.lark
optimade/grammar/v1.2.0.lark
optimade/models/__init__.py
optimade/models/baseinfo.py
optimade/models/entries.py
optimade/models/index_metadb.py
optimade/models/jsonapi.py
optimade/models/links.py
optimade/models/optimade_json.py
optimade/models/references.py
optimade/models/responses.py
optimade/models/structures.py
optimade/models/types.py
optimade/models/utils.py
optimade/server/__init__.py
optimade/server/config.py
optimade/server/exception_handlers.py
optimade/server/exceptions.py
optimade/server/index_links.json
optimade/server/logger.py
optimade/server/main.py
optimade/server/main_index.py
optimade/server/middleware.py
optimade/server/query_params.py
optimade/server/schemas.py
optimade/server/warnings.py
optimade/server/data/__init__.py
optimade/server/data/providers.json
optimade/server/data/test_links.json
optimade/server/data/test_references.json
optimade-1.3.1.dist-info/licenses/LICENSE
optimade-1.3.1.dist-info/METADATA
optimade-1.3.1.dist-info/WHEEL
optimade-1.3.1.dist-info/entry_points.txt
optimade-1.3.1.dist-info/top_level.txt
optimade-1.3.1.dist-info/RECORD
