Metadata-Version: 2.4
Name: optimade
Version: 1.3.1
Summary: Tools for implementing and consuming OPTIMADE APIs.
Author-email: OPTIMADE development team <dev@optimade.org>
License-Expression: MIT
Project-URL: Homepage, https://github.com/Materials-Consortia/optimade-python-tools
Project-URL: Bug Tracker, https://github.com/Materials-Consortia/optimade-python-tools/issues
Project-URL: Documentation, https://optimade.org/optimade-python-tools
Keywords: optimade,jsonapi,materials
Classifier: Development Status :: 4 - Beta
Classifier: Programming Language :: Python :: 3 :: Only
Classifier: Programming Language :: Python :: 3.10
Classifier: Programming Language :: Python :: 3.11
Classifier: Programming Language :: Python :: 3.12
Classifier: Programming Language :: Python :: 3.13
Classifier: Intended Audience :: Developers
Classifier: Intended Audience :: Science/Research
Classifier: Topic :: Database
Classifier: Topic :: Scientific/Engineering
Classifier: Topic :: Database :: Database Engines/Servers
Classifier: Topic :: Database :: Front-Ends
Requires-Python: >=3.10
License-File: LICENSE
Requires-Dist: lark~=1.1
Requires-Dist: pydantic[email]~=2.2
Requires-Dist: pydantic-settings~=2.0
Requires-Dist: requests~=2.28
Provides-Extra: elastic
Requires-Dist: elasticsearch-dsl<8.0,~=7.4; extra == "elastic"
Requires-Dist: elasticsearch~=7.17; extra == "elastic"
Provides-Extra: mongo
Requires-Dist: pymongo~=4.0; extra == "mongo"
Requires-Dist: mongomock~=4.1; extra == "mongo"
Provides-Extra: server
Requires-Dist: uvicorn[standard]~=0.19; extra == "server"
Requires-Dist: fastapi>=0.103.1; extra == "server"
Requires-Dist: starlette>=0.38.3,~=0.38; extra == "server"
Requires-Dist: pyyaml~=6.0; extra == "server"
Requires-Dist: optimade[mongo]; extra == "server"
Provides-Extra: aiida
Requires-Dist: aiida-core~=2.1; extra == "aiida"
Provides-Extra: http-client
Requires-Dist: httpx~=0.23; extra == "http-client"
Requires-Dist: rich<15,>=13; extra == "http-client"
Requires-Dist: click~=8.1; extra == "http-client"
Provides-Extra: ase
Requires-Dist: ase~=3.22; extra == "ase"
Provides-Extra: cif
Requires-Dist: numpy<3.0,>=1.22; extra == "cif"
Provides-Extra: pymatgen
Requires-Dist: pymatgen>=2022; python_version < "3.13" and extra == "pymatgen"
Requires-Dist: pandas~=2.2; extra == "pymatgen"
Provides-Extra: jarvis
Requires-Dist: jarvis-tools!=2024.4.20,!=2024.4.30,>=2023.1.8; python_version < "3.13" and extra == "jarvis"
Provides-Extra: client
Requires-Dist: optimade[cif]; extra == "client"
Provides-Extra: docs
Requires-Dist: mike~=2.0; extra == "docs"
Requires-Dist: mkdocs~=1.6; extra == "docs"
Requires-Dist: mkdocs-autorefs~=1.2; extra == "docs"
Requires-Dist: mkdocs-awesome-pages-plugin~=2.8; extra == "docs"
Requires-Dist: mkdocs-material~=9.0; extra == "docs"
Requires-Dist: mkdocstrings[python]~=0.26; extra == "docs"
Requires-Dist: griffe~=1.13; extra == "docs"
Provides-Extra: testing
Requires-Dist: build~=1.0; extra == "testing"
Requires-Dist: jsondiff~=2.0; extra == "testing"
Requires-Dist: pytest~=8.3; extra == "testing"
Requires-Dist: pytest-asyncio<2.0,>=0.25; extra == "testing"
Requires-Dist: pytest-cov<8,>=6; extra == "testing"
Requires-Dist: optimade[server]; extra == "testing"
Provides-Extra: dev
Requires-Dist: mypy~=1.0; extra == "dev"
Requires-Dist: pre-commit<5,>=3; extra == "dev"
Requires-Dist: invoke~=2.0; extra == "dev"
Requires-Dist: types-requests; extra == "dev"
Requires-Dist: types-pyyaml; extra == "dev"
Requires-Dist: ruff~=0.1; extra == "dev"
Requires-Dist: optimade[client,docs,http-client,testing]; extra == "dev"
Provides-Extra: http-client
Requires-Dist: optimade[http-client]; extra == "http-client"
Provides-Extra: all
Requires-Dist: optimade[aiida,ase,client,dev,elastic,http-client,jarvis,pymatgen]; extra == "all"
Dynamic: license-file
